[
    {
        "Ticker": "ANET",
        "Trade Date": "2025-07-02",
        "Decision": "SELL",
        "Targeted Price": "90"
    },
    {
        "Ticker": "CRM",
        "Trade Date": "2025-07-02",
        "Decision": "HOLD",
        "Targeted Price": "NO"
    },
    {
        "Ticker": "DAL",
        "Trade Date": "2025-07-02",
        "Decision": "HOLD",
        "Targeted Price": "NO"
    },
    {
        "Ticker": "SMCI",
        "Trade Date": "2025-07-02",
        "Decision": "BUY",
        "Targeted Price": "NO"
    },
    {
        "Ticker": "UAL",
        "Trade Date": "2025-07-02",
        "Decision": "SELL",
        "Targeted Price": "NO"
    }
]